README
deluge_client_async.py
setup.py
deluge_client_async.egg-info/PKG-INFO
deluge_client_async.egg-info/SOURCES.txt
deluge_client_async.egg-info/dependency_links.txt
deluge_client_async.egg-info/requires.txt
deluge_client_async.egg-info/top_level.txt