Metadata-Version: 1.0
Name: deluge-client-async
Version: 0.1.0
Summary: An asyncio client to deluge.
Home-page: http://github.com/allseeingeyetolledewesew/deluge_client_async
Author: AllSeeingEyeTolledEweSew
Author-email: allseeingeyetolledewesew@protonmail.com
License: Unlicense
Platform: UNKNOWN
